{
  "info": {
    "_postman_id": "b0d6e0fb-3b5d-41d3-8c11-870f9a6f7c7e",
    "name": "library-api",
    "schema": "https://schema.getpostman.com/json/collection/v2.1.0/collection.json"
  },
  "item": [
    {
      "name": "Public",
      "item": [
        {
          "name": "Health",
          "request": {
            "method": "GET",
            "header": [],
            "url": {
              "raw": "{{base_url}}/health",
              "host": [
                "{{base_url}}"
              ],
              "path": [
                "health"
              ]
            }
          }
        },
        {
          "name": "Register",
          "request": {
            "method": "POST",
            "header": [
              {
                "key": "Content-Type",
                "value": "application/json",
                "type": "text"
              }
            ],
            "url": {
              "raw": "{{base_url}}/auth/register",
              "host": [
                "{{base_url}}"
              ],
              "path": [
                "auth",
                "register"
              ]
            },
            "body": {
              "mode": "raw",
              "raw": "{\n  \"email\": \"user@example.com\",\n  \"password\": \"Password123!\",\n  \"first_name\": \"Test\",\n  \"last_name\": \"User\"\n}"
            }
          }
        },
        {
          "name": "Activate account",
          "request": {
            "method": "GET",
            "header": [],
            "url": {
              "raw": "{{base_url}}/auth/activate?token={{activation_token}}",
              "host": [
                "{{base_url}}"
              ],
              "path": [
                "auth",
                "activate"
              ],
              "query": [
                {
                  "key": "token",
                  "value": "{{activation_token}}"
                }
              ]
            }
          }
        },
        {
          "name": "Login",
          "request": {
            "method": "POST",
            "header": [
              {
                "key": "Content-Type",
                "value": "application/json",
                "type": "text"
              }
            ],
            "url": {
              "raw": "{{base_url}}/auth/login",
              "host": [
                "{{base_url}}"
              ],
              "path": [
                "auth",
                "login"
              ]
            },
            "body": {
              "mode": "raw",
              "raw": "{\n  \"email\": \"user@example.com\",\n  \"password\": \"Password123!\"\n}"
            }
          }
        }
      ]
    },
    {
      "name": "Books",
      "item": [
        {
          "name": "GetBooks (basic)",
          "request": {
            "method": "GET",
            "header": [
              {
                "key": "Content-Type",
                "value": "application/json",
                "type": "text"
              }
            ],
            "url": {
              "raw": "{{base_url}}/books",
              "host": [
                "{{base_url}}"
              ],
              "path": [
                "books"
              ]
            }
          }
        },
        {
          "name": "Search books",
          "request": {
            "method": "GET",
            "header": [
              {
                "key": "Content-Type",
                "value": "application/json",
                "type": "text"
              }
            ],
            "url": {
              "raw": "{{base_url}}/books?search=harry",
              "host": [
                "{{base_url}}"
              ],
              "path": [
                "books"
              ],
              "query": [
                {
                  "key": "search",
                  "value": "harry"
                }
              ]
            }
          }
        },
        {
          "name": "Books by genre",
          "request": {
            "method": "GET",
            "header": [
              {
                "key": "Content-Type",
                "value": "application/json",
                "type": "text"
              }
            ],
            "url": {
              "raw": "{{base_url}}/books?genre_id=1",
              "host": [
                "{{base_url}}"
              ],
              "path": [
                "books"
              ],
              "query": [
                {
                  "key": "genre_id",
                  "value": "1"
                }
              ]
            }
          }
        },
        {
          "name": "Books in stock (paged)",
          "request": {
            "method": "GET",
            "header": [
              {
                "key": "Content-Type",
                "value": "application/json",
                "type": "text"
              }
            ],
            "url": {
              "raw": "{{base_url}}/books?in_stock=1&page=1&limit=10",
              "host": [
                "{{base_url}}"
              ],
              "path": [
                "books"
              ],
              "query": [
                {
                  "key": "in_stock",
                  "value": "1"
                },
                {
                  "key": "page",
                  "value": "1"
                },
                {
                  "key": "limit",
                  "value": "10"
                }
              ]
            }
          }
        }
      ]
    },
    {
      "name": "Cart",
      "item": [
        {
          "name": "GetCartItem",
          "request": {
            "method": "GET",
            "header": [
              {
                "key": "Authorization",
                "value": "Bearer {{token}}",
                "type": "text"
              },
              {
                "key": "Content-Type",
                "value": "application/json",
                "type": "text"
              }
            ],
            "url": {
              "raw": "{{base_url}}/cart",
              "host": [
                "{{base_url}}"
              ],
              "path": [
                "cart"
              ]
            }
          }
        },
        {
          "name": "AddToCart",
          "request": {
            "method": "POST",
            "header": [
              {
                "key": "Authorization",
                "value": "Bearer {{token}}",
                "type": "text"
              },
              {
                "key": "Content-Type",
                "value": "application/json",
                "type": "text"
              }
            ],
            "url": {
              "raw": "{{base_url}}/cart",
              "host": [
                "{{base_url}}"
              ],
              "path": [
                "cart"
              ]
            },
            "body": {
              "mode": "raw",
              "raw": "{\n  \"book_id\": 1,\n  \"quantity\": 1\n}"
            }
          }
        },
        {
          "name": "UpdateCartItem",
          "request": {
            "method": "PUT",
            "header": [
              {
                "key": "Authorization",
                "value": "Bearer {{token}}",
                "type": "text"
              },
              {
                "key": "Content-Type",
                "value": "application/json",
                "type": "text"
              }
            ],
            "url": {
              "raw": "{{base_url}}/cart",
              "host": [
                "{{base_url}}"
              ],
              "path": [
                "cart"
              ]
            },
            "body": {
              "mode": "raw",
              "raw": "{\n  \"book_id\": 1,\n  \"quantity\": 2\n}"
            }
          }
        },
        {
          "name": "RemoveFromCart",
          "request": {
            "method": "DELETE",
            "header": [
              {
                "key": "Authorization",
                "value": "Bearer {{token}}",
                "type": "text"
              }
            ],
            "url": {
              "raw": "{{base_url}}/cart/1",
              "host": [
                "{{base_url}}"
              ],
              "path": [
                "cart",
                "1"
              ]
            }
          }
        }
      ]
    },
    {
      "name": "Checkout",
      "item": [
        {
          "name": "CheckOut (Cart to loan)",
          "request": {
            "method": "POST",
            "header": [
              {
                "key": "Authorization",
                "value": "Bearer {{token}}",
                "type": "text"
              },
              {
                "key": "Content-Type",
                "value": "application/json",
                "type": "text"
              }
            ],
            "url": {
              "raw": "{{base_url}}/checkout",
              "host": [
                "{{base_url}}"
              ],
              "path": [
                "checkout"
              ]
            },
            "body": {
              "mode": "raw",
              "raw": "{}"
            }
          }
        }
      ]
    },
    {
      "name": "Loans (user)",
      "item": [
        {
          "name": "GetMyLoans",
          "request": {
            "method": "GET",
            "header": [
              {
                "key": "Authorization",
                "value": "Bearer {{token}}",
                "type": "text"
              },
              {
                "key": "Content-Type",
                "value": "application/json",
                "type": "text"
              }
            ],
            "url": {
              "raw": "{{base_url}}/loans",
              "host": [
                "{{base_url}}"
              ],
              "path": [
                "loans"
              ]
            }
          }
        },
        {
          "name": "GetLoanDetail",
          "request": {
            "method": "GET",
            "header": [
              {
                "key": "Authorization",
                "value": "Bearer {{token}}",
                "type": "text"
              },
              {
                "key": "Content-Type",
                "value": "application/json",
                "type": "text"
              }
            ],
            "url": {
              "raw": "{{base_url}}/loans/1",
              "host": [
                "{{base_url}}"
              ],
              "path": [
                "loans",
                "1"
              ]
            }
          }
        },
        {
          "name": "GetLoanQR",
          "request": {
            "method": "GET",
            "header": [
              {
                "key": "Authorization",
                "value": "Bearer {{token}}",
                "type": "text"
              }
            ],
            "url": {
              "raw": "{{base_url}}/loans/1/qr.png",
              "host": [
                "{{base_url}}"
              ],
              "path": [
                "loans",
                "1",
                "qr.png"
              ]
            }
          }
        },
        {
          "name": "RenewLoan (user)",
          "request": {
            "method": "POST",
            "header": [
              {
                "key": "Authorization",
                "value": "Bearer {{token}}",
                "type": "text"
              },
              {
                "key": "Content-Type",
                "value": "application/json",
                "type": "text"
              }
            ],
            "url": {
              "raw": "{{base_url}}/loans/1/renew",
              "host": [
                "{{base_url}}"
              ],
              "path": [
                "loans",
                "1",
                "renew"
              ]
            }
          }
        }
      ]
    },
    {
      "name": "Reviews (user)",
      "item": [
        {
          "name": "GetReviewsByBook",
          "request": {
            "method": "GET",
            "header": [
              {
                "key": "Authorization",
                "value": "Bearer {{token}}",
                "type": "text"
              }
            ],
            "url": {
              "raw": "{{base_url}}/reviews/book/1",
              "host": [
                "{{base_url}}"
              ],
              "path": [
                "reviews",
                "book",
                "1"
              ]
            }
          }
        },
        {
          "name": "Post review",
          "request": {
            "method": "POST",
            "header": [
              {
                "key": "Authorization",
                "value": "Bearer {{token}}",
                "type": "text"
              },
              {
                "key": "Content-Type",
                "value": "application/json",
                "type": "text"
              }
            ],
            "url": {
              "raw": "{{base_url}}/reviews",
              "host": [
                "{{base_url}}"
              ],
              "path": [
                "reviews"
              ]
            },
            "body": {
              "mode": "raw",
              "raw": "{\n  \"book_id\": 1,\n  \"rating\": 5,\n  \"content\": \"Hay lắm!\"\n}"
            }
          }
        },
        {
          "name": "Edit review",
          "request": {
            "method": "PUT",
            "header": [
              {
                "key": "Authorization",
                "value": "Bearer {{token}}",
                "type": "text"
              },
              {
                "key": "Content-Type",
                "value": "application/json",
                "type": "text"
              }
            ],
            "url": {
              "raw": "{{base_url}}/reviews/1",
              "host": [
                "{{base_url}}"
              ],
              "path": [
                "reviews",
                "1"
              ]
            },
            "body": {
              "mode": "raw",
              "raw": "{\n  \"rating\": 4,\n  \"content\": \"S\u00e1ch \u1ed5n\"\n}"
            }
          }
        },
        {
          "name": "Delete review",
          "request": {
            "method": "DELETE",
            "header": [
              {
                "key": "Authorization",
                "value": "Bearer {{token}}",
                "type": "text"
              }
            ],
            "url": {
              "raw": "{{base_url}}/reviews/1",
              "host": [
                "{{base_url}}"
              ],
              "path": [
                "reviews",
                "1"
              ]
            }
          }
        }
      ]
    },
    {
      "name": "Invoices (user)",
      "item": [
        {
          "name": "GetMyInvoices",
          "request": {
            "method": "GET",
            "header": [
              {
                "key": "Authorization",
                "value": "Bearer {{token}}",
                "type": "text"
              },
              {
                "key": "Content-Type",
                "value": "application/json",
                "type": "text"
              }
            ],
            "url": {
              "raw": "{{base_url}}/invoices",
              "host": [
                "{{base_url}}"
              ],
              "path": [
                "invoices"
              ]
            }
          }
        },
        {
          "name": "GetInvoiceDetail",
          "request": {
            "method": "GET",
            "header": [
              {
                "key": "Authorization",
                "value": "Bearer {{token}}",
                "type": "text"
              }
            ],
            "url": {
              "raw": "{{base_url}}/invoices/1",
              "host": [
                "{{base_url}}"
              ],
              "path": [
                "invoices",
                "1"
              ]
            }
          }
        }
      ]
    },
    {
      "name": "Transactions (user)",
      "item": [
        {
          "name": "GetMyTransactions",
          "request": {
            "method": "GET",
            "header": [
              {
                "key": "Authorization",
                "value": "Bearer {{token}}",
                "type": "text"
              },
              {
                "key": "Content-Type",
                "value": "application/json",
                "type": "text"
              }
            ],
            "url": {
              "raw": "{{base_url}}/transactions",
              "host": [
                "{{base_url}}"
              ],
              "path": [
                "transactions"
              ]
            }
          }
        },
        {
          "name": "GetMyTransactions (by type)",
          "request": {
            "method": "GET",
            "header": [
              {
                "key": "Authorization",
                "value": "Bearer {{token}}",
                "type": "text"
              },
              {
                "key": "Content-Type",
                "value": "application/json",
                "type": "text"
              }
            ],
            "url": {
              "raw": "{{base_url}}/transactions?type=payment",
              "host": [
                "{{base_url}}"
              ],
              "path": [
                "transactions"
              ],
              "query": [
                {
                  "key": "type",
                  "value": "payment"
                }
              ]
            }
          }
        }
      ]
    },
    {
      "name": "Admin",
      "item": [
        {
          "name": "AdminScan",
          "request": {
            "method": "POST",
            "header": [
              {
                "key": "Authorization",
                "value": "Bearer {{admin_token}}",
                "type": "text"
              },
              {
                "key": "Content-Type",
                "value": "application/json",
                "type": "text"
              }
            ],
            "url": {
              "raw": "{{base_url}}/admin/scan",
              "host": [
                "{{base_url}}"
              ],
              "path": [
                "admin",
                "scan"
              ]
            },
            "body": {
              "mode": "raw",
              "raw": "{\n  \"token\": \"{{pickup_token}}\"\n}"
            }
          }
        },
        {
          "name": "Admin Checkout (Loan to physical)",
          "request": {
            "method": "POST",
            "header": [
              {
                "key": "Authorization",
                "value": "Bearer {{admin_token}}",
                "type": "text"
              },
              {
                "key": "Content-Type",
                "value": "application/json",
                "type": "text"
              }
            ],
            "url": {
              "raw": "{{base_url}}/admin/loans/1/confirm",
              "host": [
                "{{base_url}}"
              ],
              "path": [
                "admin",
                "loans",
                "1",
                "confirm"
              ]
            }
          }
        },
        {
          "name": "Admin Renew loan",
          "request": {
            "method": "POST",
            "header": [
              {
                "key": "Authorization",
                "value": "Bearer {{admin_token}}",
                "type": "text"
              },
              {
                "key": "Content-Type",
                "value": "application/json",
                "type": "text"
              }
            ],
            "url": {
              "raw": "{{base_url}}/admin/loans/1/renew",
              "host": [
                "{{base_url}}"
              ],
              "path": [
                "admin",
                "loans",
                "1",
                "renew"
              ]
            }
          }
        },
        {
          "name": "Admin Return loan",
          "request": {
            "method": "POST",
            "header": [
              {
                "key": "Authorization",
                "value": "Bearer {{admin_token}}",
                "type": "text"
              },
              {
                "key": "Content-Type",
                "value": "application/json",
                "type": "text"
              }
            ],
            "url": {
              "raw": "{{base_url}}/admin/loans/1/return",
              "host": [
                "{{base_url}}"
              ],
              "path": [
                "admin",
                "loans",
                "1",
                "return"
              ]
            }
          }
        },
        {
          "name": "Admin Cancel loan",
          "request": {
            "method": "POST",
            "header": [
              {
                "key": "Authorization",
                "value": "Bearer {{admin_token}}",
                "type": "text"
              },
              {
                "key": "Content-Type",
                "value": "application/json",
                "type": "text"
              }
            ],
            "url": {
              "raw": "{{base_url}}/admin/loans/1/cancel",
              "host": [
                "{{base_url}}"
              ],
              "path": [
                "admin",
                "loans",
                "1",
                "cancel"
              ]
            }
          }
        },
        {
          "name": "Hide review",
          "request": {
            "method": "PUT",
            "header": [
              {
                "key": "Authorization",
                "value": "Bearer {{admin_token}}",
                "type": "text"
              }
            ],
            "url": {
              "raw": "{{base_url}}/admin/reviews/1/hide",
              "host": [
                "{{base_url}}"
              ],
              "path": [
                "admin",
                "reviews",
                "1",
                "hide"
              ]
            }
          }
        },
        {
          "name": "Show review",
          "request": {
            "method": "PUT",
            "header": [
              {
                "key": "Authorization",
                "value": "Bearer {{admin_token}}",
                "type": "text"
              }
            ],
            "url": {
              "raw": "{{base_url}}/admin/reviews/1/show",
              "host": [
                "{{base_url}}"
              ],
              "path": [
                "admin",
                "reviews",
                "1",
                "show"
              ]
            }
          }
        },
        {
          "name": "GetInvoices (admin)",
          "request": {
            "method": "GET",
            "header": [
              {
                "key": "Authorization",
                "value": "Bearer {{admin_token}}",
                "type": "text"
              }
            ],
            "url": {
              "raw": "{{base_url}}/admin/invoices",
              "host": [
                "{{base_url}}"
              ],
              "path": [
                "admin",
                "invoices"
              ]
            }
          }
        },
        {
          "name": "MarkPaid",
          "request": {
            "method": "POST",
            "header": [
              {
                "key": "Authorization",
                "value": "Bearer {{admin_token}}",
                "type": "text"
              },
              {
                "key": "Content-Type",
                "value": "application/json",
                "type": "text"
              }
            ],
            "url": {
              "raw": "{{base_url}}/admin/invoices/1/mark-paid",
              "host": [
                "{{base_url}}"
              ],
              "path": [
                "admin",
                "invoices",
                "1",
                "mark-paid"
              ]
            },
            "body": {
              "mode": "raw",
              "raw": "{}"
            }
          }
        }
      ]
    }
  ],
  "variable": [
    {
      "key": "base_url",
      "value": "http://localhost:3000"
    },
    {
      "key": "token",
      "value": ""
    },
    {
      "key": "admin_token",
      "value": ""
    },
    {
      "key": "activation_token",
      "value": ""
    },
    {
      "key": "pickup_token",
      "value": ""
    }
  ]
}
